LICENSE
MANIFEST.in
README.rst
setup.py
waterf/__init__.py
waterf/deferred2.py
waterf/queue.py
waterf/snake.py
waterf.egg-info/PKG-INFO
waterf.egg-info/SOURCES.txt
waterf.egg-info/dependency_links.txt
waterf.egg-info/top_level.txt