Metadata-Version: 1.0
Name: waterf
Version: 2.1.2
Summary: Chaining tasks on Google Appengine's (GAE) taskqueue.
Home-page: http://github.com/kaste/waterf
Author: herr kaste
Author-email: herr.kaste@gmail.com
License: BSD
Download-URL: http://github.com/kaste/waterf/tarball/master#egg=waterf-dev
Keywords: google appengine gae taskqueue deferred
Platform: UNKNOWN
Classifier: Development Status :: 4 - Beta
Classifier: Environment :: Web Environment
Classifier: Intended Audience :: Developers
Classifier: License :: OSI Approved :: BSD License
Classifier: Operating System :: OS Independent
Classifier: Programming Language :: Python
Classifier: Topic :: Internet :: WWW/HTTP
Classifier: Topic :: Software Development :: Libraries
